utils/__init__.py
utils_vychod-0.0.1.dist-info/LICENSE
utils_vychod-0.0.1.dist-info/METADATA
utils_vychod-0.0.1.dist-info/WHEEL
utils_vychod-0.0.1.dist-info/top_level.txt
utils_vychod-0.0.1.dist-info/RECORD
