Metadata-Version: 2.1
Name: utils-vychod
Version: 0.0.1
Summary: A package of personal daily utils code
Home-page: https://github.com/pypa/sampleproject
Author: Vychod
Author-email: weyounglc@163.com
Classifier: Programming Language :: Python :: 3
Classifier: License :: OSI Approved :: MIT License
Classifier: Operating System :: OS Independent
License-File: LICENSE
